rsult/__init__.py
rsult/api.py
rsult/core.py
rsult/types.py
rsult-1.0.1.dist-info/METADATA
rsult-1.0.1.dist-info/WHEEL
rsult-1.0.1.dist-info/RECORD
