Metadata-Version: 2.4
Name: rsult
Version: 1.0.1
Summary: Rust like `Result[T, E]` support for python!
Requires-Python: >=3.13
